nekoite_be_core/__init__.py
nekoite_be_core/cache.py
nekoite_be_core/db.py
nekoite_be_core/errors.py
nekoite_be_core/util.py
nekoite_be_core/view.py
nekoite_be_core/adapters/__init__.py
nekoite_be_core/adapters/flaskadapter.py
nekoite_be_core/types/__init__.py
nekoite_be_core/types/fields.py
nekoite_be_core/types/interfaces.py
nekoite_be_core-0.1.4.dist-info/LICENSE
nekoite_be_core-0.1.4.dist-info/METADATA
nekoite_be_core-0.1.4.dist-info/WHEEL
nekoite_be_core-0.1.4.dist-info/top_level.txt
nekoite_be_core-0.1.4.dist-info/RECORD
